pycftools.py
pycftools-0.2.8.dist-info/LICENSE.txt
pycftools-0.2.8.dist-info/METADATA
pycftools-0.2.8.dist-info/WHEEL
pycftools-0.2.8.dist-info/top_level.txt
pycftools-0.2.8.dist-info/RECORD
