Metadata-Version: 2.1
Name: pycftools
Version: 0.2.8
Summary: This library provides access to all cftools api methods. It is a kind of wrapper for all methods.
Home-page: https://github.com/Exordio/pycftools
Author: Ivan Golubev
Author-email: wecatorz@gmail.com
License: UNKNOWN
Platform: UNKNOWN
Classifier: Programming Language :: Python :: 3
Classifier: License :: OSI Approved :: MIT License
Classifier: Operating System :: OS Independent
License-File: LICENSE.txt
Requires-Dist: requests (>=2.26.0)
